0247_Sequence/0247_sequence.v
// Sequence generator for the sequence 0-2-4-7

module _0247_sequence (
    input clk,
    input rst,
    output reg [2:0] q
);

  always @(posedge clk or posedge rst) begin
    if (rst) begin
      q <= 3'b000;
    end else begin

      case (q)
        3'b000:  q <= 3'b010;  // 0 -> 2
        3'b010:  q <= 3'b100;  // 2 -> 4
        3'b100:  q <= 3'b111;  // 4 -> 7
        3'b111:  q <= 3'b000;  // 7 -> 0
        default: q <= 3'b000;
      endcase
    end
  end

endmodule

0247_Sequence/0247_sequence_tb.v
`timescale 1ns / 1ps

module _0247_sequence_tb ();

  reg clk, rst;
  wire [2:0] q;

  _0247_sequence uut (
      clk,
      rst,
      q
  );

  initial begin
    clk = 0;
    forever #5 clk = ~clk;
  end

  initial begin
    $dumpfile("0247_sequence.vcd");
    $dumpvars(0, _0247_sequence_tb);

    #6;
    rst = 1;
    #4;
    rst = 0;

    #55;
    rst = 1;
    #5;
    rst = 0;

    #15;
    $finish;

  end

endmodule

0247_Sequence/0247_sequence.vcd
$date
	Tue Oct 29 21:06:05 2024
$end
$version
	Icarus Verilog
$end
$timescale
	1ps
$end
$scope module _0247_sequence_tb $end
$var wire 3 ! q [2:0] $end
$var reg 1 " clk $end
$var reg 1 # rst $end
$scope module uut $end
$var wire 1 " clk $end
$var wire 1 # rst $end
$var reg 3 $ q [2:0] $end
$upscope $end
$upscope $end
$enddefinitions $end
$comment Show the parameter values. $end
$dumpall
$end
#0
$dumpvars
bx $
x#
0"
bx !
$end
#5000
b0 !
b0 $
1"
#6000
1#
#10000
0#
0"
#15000
b10 !
b10 $
1"
#20000
0"
#25000
b100 !
b100 $
1"
#30000
0"
#35000
b111 !
b111 $
1"
#40000
0"
#45000
b0 !
b0 $
1"
#50000
0"
#55000
b10 !
b10 $
1"
#60000
0"
#65000
b0 !
b0 $
1"
1#
#70000
0"
0#
#75000
b10 !
b10 $
1"
#80000
0"
#85000
b100 !
b100 $
1"
