SIPO_Shift_Register/sipo_shift.v
module sipo_shift (
    input clk,
    input rst,
    input serial_in,
    output reg [3:0] q
);

  always @(posedge clk or posedge rst) begin

    if (rst) begin
      q <= 4'b0000;
    end else begin
      q <= {serial_in, q[3:1]};
    end

  end

endmodule

SIPO_Shift_Register/sipo_shift_tb.v
`timescale 1ns / 1ps

module sipo_shift_tb ();

  reg clk, rst, serial_in;
  wire [3:0] q;

  sipo_shift uut (
      clk,
      rst,
      serial_in,
      q
  );

  initial begin
    clk = 0;
    forever #5 clk = ~clk;
  end

  initial begin
    $dumpfile("sipo_shift.vcd");
    $dumpvars(0, sipo_shift_tb);
    serial_in = 0;
    rst = 1;
    #5;
    rst = 0;

    #5;
    serial_in = 1;
    #10;
    serial_in = 0;
    #10;
    serial_in = 0;
    #10;
    serial_in = 1;
    #30;
    rst = 1;
    #5;
    rst = 0;

    #5;
    $finish;

  end

endmodule

SIPO_Shift_Register/sipo_shift.vcd
$date
	Sun Nov  3 14:31:28 2024
$end
$version
	Icarus Verilog
$end
$timescale
	1ps
$end
$scope module sipo_shift_tb $end
$var wire 4 ! q [3:0] $end
$var reg 1 " clk $end
$var reg 1 # rst $end
$var reg 1 $ serial_in $end
$scope module uut $end
$var wire 1 " clk $end
$var wire 1 # rst $end
$var wire 1 $ serial_in $end
$var reg 4 % q [3:0] $end
$upscope $end
$upscope $end
$enddefinitions $end
$comment Show the parameter values. $end
$dumpall
$end
#0
$dumpvars
b0 %
0$
1#
0"
b0 !
$end
#5000
0#
1"
#10000
1$
0"
#15000
b1000 !
b1000 %
1"
#20000
0"
0$
#25000
b100 !
b100 %
1"
#30000
0"
#35000
b10 !
b10 %
1"
#40000
0"
1$
#45000
b1001 !
b1001 %
1"
#50000
0"
#55000
b1100 !
b1100 %
1"
#60000
0"
#65000
b1110 !
b1110 %
1"
#70000
b0 !
b0 %
0"
1#
#75000
b1000 !
b1000 %
1"
0#
