Asynchronous_Counter_4Bit/asynchronous_counter.v
module asynchronous_counter (
    input clk,
    input rst,
    output reg [3:0] q
);

  always @(posedge clk or posedge rst) begin
    if (rst) begin
      q <= 4'b0000;
    end else begin

      q[0] <= ~q[0];  // Toggle the LSB
      q[1] <= q[0] ? ~q[1] : q[1];  // Toggle q[1] if q[0] toggles from 1 to 0
      q[2] <= (q[1] & q[0]) ? ~q[2] : q[2];  // Toggle q[2] if q[0] and q[1] toggle from 1 to 0
      q[3] <= (q[2] & q[1] & q[0]) ? ~q[3] : q[3]; // Toggle q[3] if q[2], q[1] and q[0] toggle from 1 to 0

    end
  end

endmodule

Asynchronous_Counter_4Bit/asynchronous_counter_tb.v
`timescale 1ns / 1ps

module asynchronous_counter_tb ();
  reg clk, rst;
  wire [3:0] q;

  asynchronous_counter uut (
      clk,
      rst,
      q
  );

  initial begin
    clk = 0;
    forever #5 clk = ~clk;
  end

  initial begin
    $dumpfile("asynchronous_counter.vcd");
    $dumpvars(0, asynchronous_counter_tb);

    rst = 1;
    #10;
    rst = 0;

    #65;
    rst = 1;
    #5;
    rst = 0;
    #100;
    $finish;
  end

endmodule

Asynchronous_Counter_4Bit/asynchronous_counter.vcd
$date
	Thu Oct 31 22:48:38 2024
$end
$version
	Icarus Verilog
$end
$timescale
	1ps
$end
$scope module asynchronous_counter_tb $end
$var wire 4 ! q [3:0] $end
$var reg 1 " clk $end
$var reg 1 # rst $end
$scope module uut $end
$var wire 1 " clk $end
$var wire 1 # rst $end
$var reg 4 $ q [3:0] $end
$upscope $end
$upscope $end
$enddefinitions $end
$comment Show the parameter values. $end
$dumpall
$end
#0
$dumpvars
b0 $
1#
0"
b0 !
$end
#5000
1"
#10000
0"
0#
#15000
b1 !
b1 $
1"
#20000
0"
#25000
b10 !
b10 $
1"
#30000
0"
#35000
b11 !
b11 $
1"
#40000
0"
#45000
b100 !
b100 $
1"
#50000
0"
#55000
b101 !
b101 $
1"
#60000
0"
#65000
b110 !
b110 $
1"
#70000
0"
#75000
b0 !
b0 $
1"
1#
#80000
0"
0#
#85000
b1 !
b1 $
1"
#90000
0"
#95000
b10 !
b10 $
1"
#100000
0"
#105000
b11 !
b11 $
1"
#110000
0"
#115000
b100 !
b100 $
1"
#120000
0"
#125000
b101 !
b101 $
1"
#130000
0"
#135000
b110 !
b110 $
1"
#140000
0"
#145000
b111 !
b111 $
1"
#150000
0"
#155000
b1000 !
b1000 $
1"
#160000
0"
#165000
b1001 !
b1001 $
1"
#170000
0"
#175000
b1010 !
b1010 $
1"
