Ring_Counter/ring_counter.v
// N bit ring counter
module ring_counter #(
    parameter N = 4
) (
    input clk,
    input rst,
    output reg [N-1:0] q
);

  always @(posedge clk or posedge rst) begin

    if (rst) begin
      q <= {{N - 1{1'b0}}, 1'b1};  // At least one 1 has to be there for the ring counter to work
    end else begin
      q <= {q[0], q[N-1:1]};
    end

  end

endmodule

Ring_Counter/ring_counter_tb.v
`timescale 1ns / 1ps

module ring_counter_tb ();
  parameter N = 4;

  reg clk, rst;
  wire [N-1:0] q;

  ring_counter #(
      .N(N)
  ) uut (
      clk,
      rst,
      q
  );

  initial begin
    clk = 0;
    forever #5 clk = ~clk;
  end

  initial begin
    $dumpfile("ring_counter.vcd");
    $dumpvars(0, ring_counter_tb);
    rst = 1;
    #5;
    rst = 0;

    repeat (2 * N) @(posedge clk);  // Wait for 2 cycles of full rotation

    $finish;
  end

endmodule

Ring_Counter/ring_counter.vcd
$date
	Sun Nov  3 21:02:32 2024
$end
$version
	Icarus Verilog
$end
$timescale
	1ps
$end
$scope module ring_counter_tb $end
$var wire 4 ! q [3:0] $end
$var parameter 32 " N $end
$var reg 1 # clk $end
$var reg 1 $ rst $end
$scope module uut $end
$var wire 1 # clk $end
$var wire 1 $ rst $end
$var parameter 32 % N $end
$var reg 4 & q [3:0] $end
$upscope $end
$upscope $end
$enddefinitions $end
$comment Show the parameter values. $end
$dumpall
b100 %
b100 "
$end
#0
$dumpvars
b1 &
1$
0#
b1 !
$end
#5000
b1000 !
b1000 &
0$
1#
#10000
0#
#15000
b100 !
b100 &
1#
#20000
0#
#25000
b10 !
b10 &
1#
#30000
0#
#35000
b1 !
b1 &
1#
#40000
0#
#45000
b1000 !
b1000 &
1#
#50000
0#
#55000
b100 !
b100 &
1#
#60000
0#
#65000
b10 !
b10 &
1#
#70000
0#
#75000
b1 !
b1 &
1#
#80000
0#
#85000
b1000 !
b1000 &
1#
