Gray_Code_Counter/gray_code_counter.v
// 3 bit gray code counter

module gray_code_counter (
    input clk,
    input rst,
    output reg [2:0] q
);

  reg [2:0] bin;

  always @(posedge clk or posedge rst) begin

    if (rst) begin
      bin <= 3'b000;
    end else begin
      bin = bin + 1;
    end

  end

  always @(*) begin
    q[2] = bin[2];
    q[1] = bin[2] ^ bin[1];
    q[0] = bin[1] ^ bin[0];
  end

endmodule

Gray_Code_Counter/gray_code_counter_tb.v
`timescale 1ns / 1ps

module gray_code_counter_tb ();

  reg clk;
  reg rst;
  wire [2:0] q;

  gray_code_counter uut (
      clk,
      rst,
      q
  );

  initial begin
    clk = 0;
    forever #5 clk = ~clk;
  end

  initial begin
    $dumpfile("gray_code_counter.vcd");
    $dumpvars(0, gray_code_counter_tb);

    rst = 1;
    #5;
    rst = 0;

    #125;
    rst = 1;
    #2;
    rst = 0;

    #40;
    $finish;

  end

endmodule

Gray_Code_Counter/gray_code_counter.vcd
$date
	Tue Oct 29 22:40:49 2024
$end
$version
	Icarus Verilog
$end
$timescale
	1ps
$end
$scope module gray_code_counter_tb $end
$var wire 3 ! q [2:0] $end
$var reg 1 " clk $end
$var reg 1 # rst $end
$scope module uut $end
$var wire 1 " clk $end
$var wire 1 # rst $end
$var reg 3 $ bin [2:0] $end
$var reg 3 % q [2:0] $end
$upscope $end
$upscope $end
$enddefinitions $end
$comment Show the parameter values. $end
$dumpall
$end
#0
$dumpvars
b0 %
b0 $
1#
0"
b0 !
$end
#5000
b1 !
b1 %
b1 $
0#
1"
#10000
0"
#15000
b11 !
b11 %
b10 $
1"
#20000
0"
#25000
b10 !
b10 %
b11 $
1"
#30000
0"
#35000
b110 !
b110 %
b100 $
1"
#40000
0"
#45000
b111 !
b111 %
b101 $
1"
#50000
0"
#55000
b101 !
b101 %
b110 $
1"
#60000
0"
#65000
b100 !
b100 %
b111 $
1"
#70000
0"
#75000
b0 !
b0 %
b0 $
1"
#80000
0"
#85000
b1 !
b1 %
b1 $
1"
#90000
0"
#95000
b11 !
b11 %
b10 $
1"
#100000
0"
#105000
b10 !
b10 %
b11 $
1"
#110000
0"
#115000
b110 !
b110 %
b100 $
1"
#120000
0"
#125000
b111 !
b111 %
b101 $
1"
#130000
b0 !
b0 %
b0 $
0"
1#
#132000
0#
#135000
b1 !
b1 %
b1 $
1"
#140000
0"
#145000
b11 !
b11 %
b10 $
1"
#150000
0"
#155000
b10 !
b10 %
b11 $
1"
#160000
0"
#165000
b110 !
b110 %
b100 $
1"
