JK_FF/JK_FF.v
module JK_FF (
    input  wire clk,
    input  wire J,
    input  wire K,
    input  wire rst,
    input  wire pst,
    output reg  Q,
    output wire Q_bar
);
  assign Q_bar = ~Q;

  always @(posedge clk or posedge rst or posedge pst) begin
    if (rst) begin
      Q <= 0;
    end else if (pst) begin
      Q <= 1;
    end else begin

      case ({
        J, K
      })
        2'b00: Q <= Q;  // No change
        2'b10: Q <= 1;  // J = 1, K = 0 -> Set
        2'b01: Q <= Q;  // J  = 0, K = 1 -> Reset
        2'b11: Q <= ~Q;  // Toggle

      endcase

    end

  end

endmodule

JK_FF/JK_FF_tb.v
`timescale 1ns / 1ps

module JK_FF_tb ();

  reg clk, rst, pst, J, K;
  wire Q, Q_bar;

  JK_FF uut (
      clk,
      J,
      K,
      rst,
      pst,
      Q,
      Q_bar
  );

  initial begin
    clk = 0;
    forever #5 clk = ~clk;
  end

  initial begin
    $dumpfile("JK_FF.vcd");
    $dumpvars(0, JK_FF_tb);

    rst = 0;
    pst = 0;
    J   = 0;
    K   = 0;
    #10;

    //Testing asynchronous reset
    #2 rst = 1;
    #10;
    rst = 0;

    //Testing asynchronous preset
    #2 pst = 1;
    #10;
    pst = 0;

    //Testing FF set
    J   = 1;
    K   = 0;
    #10;

    // Testing "no change" state
    J = 0;
    K = 0;
    #10;

    // Testing FF reset
    J = 0;
    K = 1;
    #10;

    // Testing FF toggle
    J = 1;
    K = 1;
    #10;

    $finish;

  end

endmodule

JK_FF/JK_FF.vcd
$date
	Mon Oct 28 11:28:45 2024
$end
$version
	Icarus Verilog
$end
$timescale
	1ps
$end
$scope module JK_FF_tb $end
$var wire 1 ! Q_bar $end
$var wire 1 " Q $end
$var reg 1 # J $end
$var reg 1 $ K $end
$var reg 1 % clk $end
$var reg 1 & pst $end
$var reg 1 ' rst $end
$scope module uut $end
$var wire 1 # J $end
$var wire 1 $ K $end
$var wire 1 ! Q_bar $end
$var wire 1 % clk $end
$var wire 1 & pst $end
$var wire 1 ' rst $end
$var reg 1 " Q $end
$upscope $end
$upscope $end
$enddefinitions $end
$comment Show the parameter values. $end
$dumpall
$end
#0
$dumpvars
0'
0&
0%
0$
0#
x"
x!
$end
#5000
1%
#10000
0%
#12000
1!
0"
1'
#15000
1%
#20000
0%
#22000
0'
#24000
0!
1"
1&
#25000
1%
#30000
0%
#34000
1#
0&
#35000
1%
#40000
0%
#44000
0#
#45000
1%
#50000
0%
#54000
1$
#55000
1%
#60000
0%
#64000
1#
#65000
1!
0"
1%
