Encoder/encoder.v
// 8:3 One-Hot Encoder using conditional operators

module encoder (input wire [7:0] in,
                output wire [2:0] out);

  assign out =  (in == 8'b00000001) ? 3'b000 :
                (in == 8'b00000010) ? 3'b001 :
                (in == 8'b00000100) ? 3'b010 :
                (in == 8'b00001000) ? 3'b011 :
                (in == 8'b00010000) ? 3'b100 :
                (in == 8'b00100000) ? 3'b101 :
                (in == 8'b01000000) ? 3'b110 :
                (in == 8'b10000000) ? 3'b111 :
                8'bXX;
endmodule

Encoder/encoder_tb.v
// Testbench for 8:3 encoder

`timescale 1ns/1ps

module encoder_tb (
  
);
  reg [7:0] inputs;
  wire [2:0] outputs;

  encoder uut (
    .in(inputs),
    .out(outputs)
  );

  integer i;

  initial begin
    $dumpfile("encoder.vcd");
    $dumpvars(0, encoder_tb);

    for (i = 0; i < 8; i++) begin
      inputs = 8'b00000001 << i;
      #10;
    end

    $finish;
  end

endmodule

Encoder/encoder.vcd
$date
	Wed Oct 23 19:05:43 2024
$end
$version
	Icarus Verilog
$end
$timescale
	1ps
$end
$scope module encoder_tb $end
$var wire 3 ! outputs [2:0] $end
$var reg 8 " inputs [7:0] $end
$var integer 32 # i [31:0] $end
$scope module uut $end
$var wire 8 $ in [7:0] $end
$var wire 3 % out [2:0] $end
$upscope $end
$upscope $end
$enddefinitions $end
$comment Show the parameter values. $end
$dumpall
$end
#0
$dumpvars
b0 %
b1 $
b0 #
b1 "
b0 !
$end
#10000
b1 !
b1 %
b10 "
b10 $
b1 #
#20000
b10 !
b10 %
b100 "
b100 $
b10 #
#30000
b11 !
b11 %
b1000 "
b1000 $
b11 #
#40000
b100 !
b100 %
b10000 "
b10000 $
b100 #
#50000
b101 !
b101 %
b100000 "
b100000 $
b101 #
#60000
b110 !
b110 %
b1000000 "
b1000000 $
b110 #
#70000
b111 !
b111 %
b10000000 "
b10000000 $
b111 #
#80000
b1000 #
