Decoder/decoder.v
//3:8 one hot decoder

module one_hot_decoder (output wire [7:0] F,
                        input wire A, B, C);
  assign F[7] = ~A & ~B & ~C;
  assign F[6] = ~A & ~B & C;
  assign F[5] = ~A & B & ~C;
  assign F[4] = ~A & B & C;
  assign F[3] = A & ~B & ~C;
  assign F[2] = A & ~B & C;
  assign F[1] = A & B & ~C;
  assign F[0] = A & B & C;

endmodule

Decoder/decoder_tb.v
// Test bench for 3:8 one-hot decoder

`timescale 1ns/1ps

module one_hot_decoder_tb;
  reg A, B, C;
  wire [7:0] F;

  one_hot_decoder uut (
    .A(A),
    .B(B),
    .C(C),
    .F(F)
  );

integer i;

  initial begin
    $dumpfile("one_hot_decoder.vcd");
    $dumpvars(0, one_hot_decoder_tb);
    
    for (i = 0; i < 8; i = i + 1) begin
            {A, B, C} = i;
            #10;
        end

    $finish;
  end
endmodule

Decoder/decoder.vcd
$date
	Sun Oct 13 14:37:14 2024
$end
$version
	Icarus Verilog
$end
$timescale
	1ps
$end
$scope module one_hot_decoder_tb $end
$var wire 8 ! F [7:0] $end
$var reg 1 " A $end
$var reg 1 # B $end
$var reg 1 $ C $end
$var integer 32 % i [31:0] $end
$scope module uut $end
$var wire 1 " A $end
$var wire 1 # B $end
$var wire 1 $ C $end
$var wire 8 & F [7:0] $end
$upscope $end
$upscope $end
$enddefinitions $end
$comment Show the parameter values. $end
$dumpall
$end
#0
$dumpvars
b10000000 &
b0 %
0$
0#
0"
b10000000 !
$end
#10000
b1000000 !
b1000000 &
1$
b1 %
#20000
b100000 !
b100000 &
1#
0$
b10 %
#30000
b10000 !
b10000 &
1$
b11 %
#40000
b1000 !
b1000 &
1"
0#
0$
b100 %
#50000
b100 !
b100 &
1$
b101 %
#60000
b10 !
b10 &
1#
0$
b110 %
#70000
b1 !
b1 &
1$
b111 %
#80000
b1000 %
