1101_Detector_Mealy/1101_detector.v
// Sequence detector for the overlapping sequence 1101 using a Mealy machine

module detector_1101 (
    input clk,
    input rst,
    input in,
    output reg out
);
  reg [1:0] current_state, next_state;

  parameter S0 = 2'b00;  // Initial state
  parameter S1 = 2'b01;  // After detecting 1
  parameter S2 = 2'b10;  // After detecting 11
  parameter S3 = 2'b11;  // After detecting 110

  always @(*) begin

    next_state = current_state;
    out = 0;

    case (current_state)
      S0: begin
        if (in) begin
          next_state = S1;
        end
      end
      S1: begin
        if (in) begin
          next_state = S2;
        end else begin
          next_state = S0;
        end
      end
      S2: begin
        if (!in) begin
          next_state = S3;
        end
      end
      S3: begin
        if (in) begin
          next_state = S1;
          out = 1;  // Sequence 1101 has been detected
        end else begin
          next_state = S0;
        end
      end
      default: next_state = S0;
    endcase


  end

  //Updating the state
  always @(posedge clk or posedge rst) begin
    if (rst) begin
      current_state <= S0;
    end else begin
      current_state <= next_state;

    end

  end

endmodule

1101_Detector_Mealy/1101_detector_tb.v
`timescale 1ns / 1ps

module detector_1101_tb ();
  reg clk, rst, in;
  wire out;

  initial begin
    clk = 0;
    forever #5 clk = ~clk;
  end

  detector_1101 uut (
      clk,
      rst,
      in,
      out
  );

  initial begin
    $dumpfile("detector_1101.vcd");
    $dumpvars(0, detector_1101_tb);
    rst = 1;
    #5;
    rst = 0;

    #5;
    in = 1;
    #20;
    in = 0;
    #10;
    in = 1;

    #10;
    in = 0;
    #10;
    in = 1;
    #30;
    in = 0;
    #10;
    in = 1;

    #20;
    $finish;

  end

endmodule

1101_Detector_Mealy/detector_1101.vcd
$date
	Thu Nov  7 14:37:40 2024
$end
$version
	Icarus Verilog
$end
$timescale
	1ps
$end
$scope module detector_1101_tb $end
$var wire 1 ! out $end
$var reg 1 " clk $end
$var reg 1 # in $end
$var reg 1 $ rst $end
$scope module uut $end
$var wire 1 " clk $end
$var wire 1 # in $end
$var wire 1 $ rst $end
$var parameter 2 % S0 $end
$var parameter 2 & S1 $end
$var parameter 2 ' S2 $end
$var parameter 2 ( S3 $end
$var reg 2 ) current_state [1:0] $end
$var reg 2 * next_state [1:0] $end
$var reg 1 ! out $end
$upscope $end
$upscope $end
$enddefinitions $end
$comment Show the parameter values. $end
$dumpall
b11 (
b10 '
b1 &
b0 %
$end
#0
$dumpvars
b0 *
b0 )
1$
x#
0"
0!
$end
#5000
0$
1"
#10000
b1 *
1#
0"
#15000
b10 *
b1 )
1"
#20000
0"
#25000
b10 )
1"
#30000
b11 *
0"
0#
#35000
b0 *
b11 )
1"
#40000
1!
b1 *
0"
1#
#45000
b10 *
0!
b1 )
1"
#50000
b0 *
0"
0#
#55000
b0 )
1"
#60000
b1 *
0"
1#
#65000
b10 *
b1 )
1"
#70000
0"
#75000
b10 )
1"
#80000
0"
#85000
1"
#90000
b11 *
0"
0#
#95000
b0 *
b11 )
1"
#100000
1!
b1 *
0"
1#
#105000
b10 *
0!
b1 )
1"
#110000
0"
#115000
b10 )
1"
