Synchronous_Counter_4Bit/Synchronous_Counter.v
module Synchronous_Counter (
    input wire clk,
    input wire reset,
    output reg [3:0] q
);

  always @(posedge clk or posedge reset) begin
    if (reset) begin
      q <= 4'b0000;
    end else begin
      q <= q + 1;
    end
  end

endmodule

Synchronous_Counter_4Bit/Synchronous_Counter_tb.v
`timescale 1ns / 1ps

module Synchronous_Counter_tb ();

  reg clk, reset;
  wire [3:0] q;

  initial begin
    clk = 0;
    forever begin
      #5 clk = ~clk;
    end
  end

  Synchronous_Counter uut (
      clk,
      reset,
      q
  );

  initial begin
    $dumpfile("Synchronous_Counter.vcd");
    $dumpvars(0, Synchronous_Counter_tb);

    reset = 1;
    #10;

    reset = 0;  // Deasserting reset
    #100;

    #2;
    reset = 1;  //Testing asynchronous behaviour of reset
    #10;

    reset = 0;
    #50;

    $finish;


  end

endmodule

Synchronous_Counter_4Bit/Synchronous_Counter.vcd
$date
	Sun Oct 27 23:36:40 2024
$end
$version
	Icarus Verilog
$end
$timescale
	1ps
$end
$scope module Synchronous_Counter_tb $end
$var wire 4 ! q [3:0] $end
$var reg 1 " clk $end
$var reg 1 # reset $end
$scope module uut $end
$var wire 1 " clk $end
$var wire 1 # reset $end
$var reg 4 $ q [3:0] $end
$upscope $end
$upscope $end
$enddefinitions $end
$comment Show the parameter values. $end
$dumpall
$end
#0
$dumpvars
b0 $
1#
0"
b0 !
$end
#5000
1"
#10000
0"
0#
#15000
b1 !
b1 $
1"
#20000
0"
#25000
b10 !
b10 $
1"
#30000
0"
#35000
b11 !
b11 $
1"
#40000
0"
#45000
b100 !
b100 $
1"
#50000
0"
#55000
b101 !
b101 $
1"
#60000
0"
#65000
b110 !
b110 $
1"
#70000
0"
#75000
b111 !
b111 $
1"
#80000
0"
#85000
b1000 !
b1000 $
1"
#90000
0"
#95000
b1001 !
b1001 $
1"
#100000
0"
#105000
b1010 !
b1010 $
1"
#110000
0"
#112000
b0 !
b0 $
1#
#115000
1"
#120000
0"
#122000
0#
#125000
b1 !
b1 $
1"
#130000
0"
#135000
b10 !
b10 $
1"
#140000
0"
#145000
b11 !
b11 $
1"
#150000
0"
#155000
b100 !
b100 $
1"
#160000
0"
#165000
b101 !
b101 $
1"
